opengate_data/__init__.py
opengate_data/opengate_client.py
opengate_data/ai_models/__init__.py
opengate_data/ai_models/ai_models.py
opengate_data/ai_pipelines/__init__.py
opengate_data/ai_pipelines/ai_pipelines.py
opengate_data/ai_transformers/__init__.py
opengate_data/ai_transformers/ai_transformers.py
opengate_data/collection/__init__.py
opengate_data/collection/iot_bulk_collection.py
opengate_data/collection/iot_collection.py
opengate_data/collection/iot_pandas_collection.py
opengate_data/datasets/__init__.py
opengate_data/datasets/find_datasets.py
opengate_data/file_connector/__init__.py
opengate_data/file_connector/file_connector.py
opengate_data/provision/__init__.py
opengate_data/provision/asset/__init__.py
opengate_data/provision/asset/provision_asset.py
opengate_data/provision/bulk/__init__.py
opengate_data/provision/bulk/provision_bulk.py
opengate_data/provision/devices/__init__.py
opengate_data/provision/devices/provision_device.py
opengate_data/provision/processor/__init__.py
opengate_data/provision/processor/provision_processor.py
opengate_data/rules/__init__.py
opengate_data/rules/rules.py
opengate_data/searching/__init__.py
opengate_data/searching/filter.py
opengate_data/searching/search.py
opengate_data/searching/search_base.py
opengate_data/searching/select.py
opengate_data/searching/builder/__init__.py
opengate_data/searching/builder/datapoints_search.py
opengate_data/searching/builder/datasets_search.py
opengate_data/searching/builder/entities_search.py
opengate_data/searching/builder/operations_search.py
opengate_data/searching/builder/rules_search.py
opengate_data/searching/builder/timeseries_search.py
opengate_data/test/__init__.py
opengate_data/test/integration/__init__.py
opengate_data/test/integration/conftest.py
opengate_data/test/integration/steps_definitions/__init__.py
opengate_data/test/integration/steps_definitions/step_collection.py
opengate_data/test/integration/steps_definitions/step_datasets.py
opengate_data-1.12.0.dist-info/licenses/LICENSE
opengate_data-1.12.0.dist-info/METADATA
opengate_data-1.12.0.dist-info/WHEEL
opengate_data-1.12.0.dist-info/top_level.txt
opengate_data-1.12.0.dist-info/RECORD
