Metadata-Version: 2.4
Name: opengate-data
Version: 1.12.0
Summary: description
Author: amplia soluciones
Author-email: pipy@amplia.es
License: Apache License 2.0
Requires-Python: >=3.10
License-File: LICENSE
Requires-Dist: pandas
Requires-Dist: requests
Requires-Dist: jsonpath_ng
Requires-Dist: numpy
Requires-Dist: urllib3
Requires-Dist: configparser
Requires-Dist: parse
Requires-Dist: python-dotenv
Requires-Dist: datetime
Requires-Dist: flatten-dict
Requires-Dist: aiohttp
Requires-Dist: openpyxl
Requires-Dist: pyarrow
Dynamic: author
Dynamic: author-email
Dynamic: description
Dynamic: description-content-type
Dynamic: license
Dynamic: license-file
Dynamic: requires-dist
Dynamic: requires-python
Dynamic: summary
